pcoError.pyd
pydicamsdk-0.1.0.dist-info/DESCRIPTION.rst
pydicamsdk-0.1.0.dist-info/METADATA
pydicamsdk-0.1.0.dist-info/metadata.json
pydicamsdk-0.1.0.dist-info/RECORD
pydicamsdk-0.1.0.dist-info/top_level.txt
pydicamsdk-0.1.0.dist-info/WHEEL
