Metadata-Version: 2.0
Name: pydicamsdk
Version: 0.1.0
Summary: A wrapper for the pco sensicam/dicam SDK
Home-page: https://github.com/smiddy/pydicamsdk
Author: Markus J Schmidt
Author-email: schmidt@ifd.mavt.ethz.ch
License: GNU GPLv3
Platform: win-amd64
Platform: win32
Requires-Dist: numpy (>=1.9.2)
Requires-Dist: Pillow (>=2.9.0)
